{"behavior":"Ground-foraging sparrow that scratches through leaf litter for seeds, berries, and invertebrates; often feeds in flocks and sings a clear, whistled song.","common_name":"White-throated Sparrow","family":"Passerellidae","field_marks":["Large, full-bodied sparrow with a rounded head, fairly prominent conical bill, long legs, and a long narrow tail.","Crisp white throat, sharply bordered by dark malar (whisker) stripes.","Bold head pattern: black-and-white crown and eyebrow stripes, or a softer tan-and-brown striped form.","Bright yellow lores between the eye and bill.","Brown, streaked back and wings with pale wing bars; underparts gray to pale gray.","Gray bill and pinkish legs."],"habitat":"Forests and woodland edges, brushy regrowth, thickets, and pond or bog margins; also uses low shrubby cover and open ground nearby for foraging.","measurements":{"length":"6.3–7.1 in (16–18 cm)","weight":"0.8–1.1 oz (22–32 g)","wingspan":"7.9–9.1 in (20–23 cm)"},"palette":["white throat","charcoal gray","chestnut brown","black","bright yellow"],"scientific_name":"Zonotrichia albicollis","sources":[{"title":"Cornell Lab of Ornithology — White-throated Sparrow Identification","url":"https://www.allaboutbirds.org/guide/White-throated_Sparrow/id"},{"title":"Smithsonian's National Zoo and Conservation Biology Institute — White-throated Sparrow","url":"https://nationalzoo.si.edu/animals/white-throated-sparrow"}],"taxon_id":9184}